Metadata-Version: 1.0
Name: idarop
Version: 0.4.2
Summary: ROP search and visualization plugin for IDA
Home-page: https://github.com/lucasg/idarop
Author: lucasg
Author-email: lucas.georges@outlook.com
License: UNKNOWN
Platform: UNKNOWN
